spopt/BaseClass.py
spopt/__init__.py
spopt/locate/__init__.py
spopt/locate/base.py
spopt/locate/coverage.py
spopt/locate/p_center.py
spopt/locate/p_dispersion.py
spopt/locate/p_median.py
spopt/locate/util.py
spopt/region/__init__.py
spopt/region/azp.py
spopt/region/azp_util.py
spopt/region/base.py
spopt/region/components.py
spopt/region/csgraph_utils.py
spopt/region/maxp.py
spopt/region/objective_function.py
spopt/region/random_region.py
spopt/region/region_k_means.py
spopt/region/sa3.py
spopt/region/skater.py
spopt/region/spenc.py
spopt/region/util.py
spopt/region/ward.py
spopt/region/spenclib/__init__.py
spopt/region/spenclib/abstracts.py
spopt/region/spenclib/scores.py
spopt/region/spenclib/utils.py
spopt/tests/__init__.py
spopt/tests/conftest.py
spopt/tests/test_locate/test_c_p_median.py
spopt/tests/test_locate/test_clscp-so.py
spopt/tests/test_locate/test_knearest_p_median.py
spopt/tests/test_locate/test_locate_util.py
spopt/tests/test_locate/test_lscp.py
spopt/tests/test_locate/test_lscpb.py
spopt/tests/test_locate/test_mclp.py
spopt/tests/test_locate/test_p_center.py
spopt/tests/test_locate/test_p_dispersion.py
spopt/tests/test_locate/test_p_median.py
spopt/tests/test_locate/data/SF_demand_205_centroid_uniform_weight.csv
spopt/tests/test_locate/data/SF_network_distance_candidateStore_16_censusTract_205_new.csv
spopt/tests/test_locate/data/SF_store_site_16_longlat.csv
spopt/tests/test_locate/data/ServiceAreas_4.shp
spopt/tests/test_locate/data/ServiceAreas_4.shx
spopt/tests/test_locate/data/example_subject_schools.csv
spopt/tests/test_locate/data/example_subject_student_school_journeys.csv
spopt/tests/test_locate/data/example_subject_students.csv
spopt/tests/test_locate/data/lscp_cli2fac.pkl
spopt/tests/test_locate/data/lscp_fac2cli.pkl
spopt/tests/test_locate/data/lscp_geodataframe_cli2fac.pkl
spopt/tests/test_locate/data/lscp_geodataframe_fac2cli.pkl
spopt/tests/test_locate/data/lscp_preselected_loc_geodataframe_fac2cli.pkl
spopt-0.7.0.dist-info/licenses/LICENSE.txt
spopt-0.7.0.dist-info/METADATA
spopt-0.7.0.dist-info/WHEEL
spopt-0.7.0.dist-info/top_level.txt
spopt-0.7.0.dist-info/RECORD
