Metadata-Version: 2.4
Name: spopt
Version: 0.7.0
Summary: Spatial Optimization in PySAL
Author-email: "James D. Gaboardi" <jgaboardi@gmail.com>, Xin Feng <xin.feng@ucr.edu>
Maintainer: spopt contributors
License: BSD 3-Clause
Project-URL: Home, https://pysal.org/spopt/
Project-URL: Repository, https://github.com/pysal/spopt
Keywords: spatial optimization
Classifier: Programming Language :: Python :: 3
Classifier: License :: OSI Approved :: BSD License
Classifier: Operating System :: OS Independent
Classifier: Intended Audience :: Science/Research
Classifier: Topic :: Scientific/Engineering :: GIS
Requires-Python: >=3.11
License-File: LICENSE.txt
Requires-Dist: geopandas>=0.14.0
Requires-Dist: libpysal>=4.10.0
Requires-Dist: mapclassify>=2.7.0
Requires-Dist: networkx>=3.2
Requires-Dist: numpy>=1.26.0
Requires-Dist: pandas>=2.1.0
Requires-Dist: pointpats>=2.4.0
Requires-Dist: pulp>=2.8
Requires-Dist: scikit-learn>=1.4.0
Requires-Dist: scipy>=1.12.0
Requires-Dist: shapely>=2.1.0
Requires-Dist: spaghetti>=1.7.4
Requires-Dist: tqdm>=4.66.0
Provides-Extra: tests
Requires-Dist: codecov; extra == "tests"
Requires-Dist: coverage; extra == "tests"
Requires-Dist: pytest; extra == "tests"
Requires-Dist: pytest-cov; extra == "tests"
Requires-Dist: pytest-xdist; extra == "tests"
Provides-Extra: dev
Requires-Dist: pre-commit; extra == "dev"
Requires-Dist: ruff; extra == "dev"
Provides-Extra: docs
Requires-Dist: nbsphinx; extra == "docs"
Requires-Dist: numpydoc; extra == "docs"
Requires-Dist: pandoc; extra == "docs"
Requires-Dist: sphinx; extra == "docs"
Requires-Dist: sphinxcontrib-bibtex; extra == "docs"
Requires-Dist: sphinx_bootstrap_theme; extra == "docs"
Provides-Extra: notebooks
Requires-Dist: folium; extra == "notebooks"
Requires-Dist: glpk; extra == "notebooks"
Requires-Dist: inequality; extra == "notebooks"
Requires-Dist: matplotlib>=3.8; extra == "notebooks"
Requires-Dist: matplotlib-scalebar; extra == "notebooks"
Requires-Dist: overpy; extra == "notebooks"
Requires-Dist: routingpy; extra == "notebooks"
Requires-Dist: seaborn; extra == "notebooks"
Requires-Dist: watermark; extra == "notebooks"
Provides-Extra: sa3
Requires-Dist: fast_hdbscan>=0.2.2; extra == "sa3"
Requires-Dist: numba; extra == "sa3"
Dynamic: license-file
